{
  "pages": [
    {
      "pageNumber": 2,
      "words": ["house", "tree", "people", "children"]
    },
    {
      "pageNumber": 3,
      "words": ["man talking", "woman", "garden"]
    },
    {
      "pageNumber": 4,
      "words": ["two boys playing", "ball", "friends"]
    },
    {
      "pageNumber": 5,
      "words": ["family in kitchen", "mother", "father", "child"]
    },
    {
      "pageNumber": 6,
      "words": ["school", "book", "drawing", "birds singing"]
    },
    {
      "pageNumber": 7,
      "words": ["pancake", "kitchen", "food"]
    },
    {
      "pageNumber": 8,
      "words": ["pancake rolling", "hen", "duck", "road"]
    },
    {
      "pageNumber": 9,
      "words": ["monkeys", "bananas", "tree"]
    },
    {
      "pageNumber": 10,
      "words": ["children around tree", "roots", "branches"]
    },
    {
      "pageNumber": 11,
      "words": ["girl writing", "squirrel", "farmer", "plough"]
    },
    {
      "pageNumber": 12,
      "words": ["woman carrying sticks", "umbrella", "children playing under tree"]
    },
    {
      "pageNumber": 13,
      "words": ["lion", "forest", "tall trees"]
    },
    {
      "pageNumber": 14,
      "words": ["deer", "elephant", "cutting trees", "animals running"]
    },
    {
      "pageNumber": 15,
      "words": ["market", "vegetables", "fruits"]
    },
    {
      "pageNumber": 16,
      "words": ["happy face", "sad face", "friends"]
    },
    {
      "pageNumber": 17,
      "words": ["desert", "camel", "man standing"]
    },
    {
      "pageNumber": 18,
      "words": ["boy on camel", "bags", "tent"]
    },
    {
      "pageNumber": 19,
      "words": ["sick man", "medicine", "mother crying"]
    },
    {
      "pageNumber": 20,
      "words": ["sand storm", "camel sinking", "quick sand"]
    },
    {
      "pageNumber": 21,
      "words": ["palm trees", "water", "boy sleeping"]
    },
    {
      "pageNumber": 22,
      "words": ["boat", "car", "plane", "train"]
    },
    {
      "pageNumber": 23,
      "words": ["police", "man with handcuffs", "arrest"]
    },
    {
      "pageNumber": 24,
      "words": ["boy in shop", "bells", "mother hugging child"]
    },
    {
      "pageNumber": 25,
      "words": ["fruit seller", "pineapple", "money"]
    },
    {
      "pageNumber": 26,
      "words": ["boy with catapult", "birds", "tree"]
    },
    {
      "pageNumber": 27,
      "words": ["bird nest", "baby birds", "garage"]
    },
    {
      "pageNumber": 28,
      "words": ["robin", "jay bird", "garden"]
    },
    {
      "pageNumber": 29,
      "words": ["angry man", "black cat"]
    },
    {
      "pageNumber": 30,
      "words": ["village", "houses", "people"]
    },
    {
      "pageNumber": 31,
      "words": ["ladder", "broken mirror", "rocking chair"]
    }
  ]
}